aacommpy/AAComm.py
aacommpy/__init__.py
aacommpy/__version__.py
aacommpy/category.py
aacommpy/dotnetmanagement.py
aacommpy/entry_points.py
aacommpy/nugetmanagement.py
aacommpy/settings.py
aacommpy/test.py
aacommpy-0.3.8.dist-info/METADATA
aacommpy-0.3.8.dist-info/WHEEL
aacommpy-0.3.8.dist-info/entry_points.txt
aacommpy-0.3.8.dist-info/top_level.txt
aacommpy-0.3.8.dist-info/RECORD
