Metadata-Version: 2.1
Name: aacommpy
Version: 0.3.8
Summary: aacommpy - AAComm nuget package wrapper
Home-page: https://github.com/BoJl4apa/aacommpy
Author: HIEU and DB
Author-email: daniel.brousser@akribis-sys.com
License: MIT
Keywords: package development stage
Classifier: Development Status :: 5 - Production/Stable
Classifier: Intended Audience :: Developers
Classifier: Programming Language :: Python :: 3.10
Requires-Python: >=3.10.1
Requires-Dist: requests
Requires-Dist: pythonnet
